odoo/addons/stock_barcodes_automatic_entry/README.rst
odoo/addons/stock_barcodes_automatic_entry/__init__.py
odoo/addons/stock_barcodes_automatic_entry/__manifest__.py
odoo/addons/stock_barcodes_automatic_entry/i18n/stock_barcodes_automatic_entry.pot
odoo/addons/stock_barcodes_automatic_entry/readme/CONTRIBUTORS.rst
odoo/addons/stock_barcodes_automatic_entry/readme/DESCRIPTION.rst
odoo/addons/stock_barcodes_automatic_entry/readme/USAGE.rst
odoo/addons/stock_barcodes_automatic_entry/static/description/icon.png
odoo/addons/stock_barcodes_automatic_entry/static/description/index.html
odoo/addons/stock_barcodes_automatic_entry/static/src/css/button_style.css
odoo/addons/stock_barcodes_automatic_entry/static/src/js/stock_barcodes.js
odoo/addons/stock_barcodes_automatic_entry/views/assets.xml
odoo12_addon_stock_barcodes_automatic_entry-12.0.1.0.1.dist-info/METADATA
odoo12_addon_stock_barcodes_automatic_entry-12.0.1.0.1.dist-info/WHEEL
odoo12_addon_stock_barcodes_automatic_entry-12.0.1.0.1.dist-info/top_level.txt
odoo12_addon_stock_barcodes_automatic_entry-12.0.1.0.1.dist-info/RECORD
