Metadata-Version: 2.1
Name: odoo12-addon-stock-barcodes-automatic-entry
Version: 12.0.1.0.1
Summary: This module will automatically trigger the click event on a button with the class 'barcode-automatic-entry' after a barcode scanned has been processed.
Home-page: https://github.com/OCA/stock-logistics-barcode
Author: ForgeFlow S.L.,Odoo Community Association (OCA)
Author-email: support@odoo-community.org
License: AGPL-3
Platform: UNKNOWN
Classifier: Programming Language :: Python
Classifier: Framework :: Odoo
Classifier: License :: OSI Approved :: GNU Affero General Public License v3
Requires-Python: >=3.5
Requires-Dist: odoo (<12.1dev,>=12.0a)
